<?xml version="1.0" encoding="UTF-8"?><record_update table="ais_dictionary">
    <ais_dictionary action="INSERT_OR_UPDATE">
        <active>true</active>
        <auto_refresh>24</auto_refresh>
        <blocked_field/>
        <case_sensitive>false</case_sensitive>
        <data_source>x_yergb_bpm_process</data_source>
        <derived>true</derived>
        <field/>
        <label>bpm Search Profile Default Spell Check Dictionary</label>
        <last_derived/>
        <locale>en</locale>
        <name>x_yergb_bpm_bpm_search_profile_default_spell_check_dictionary</name>
        <publish_id/>
        <punctuation_sensitive>false</punctuation_sensitive>
        <state>NEW</state>
        <sys_class_name>ais_dictionary</sys_class_name>
        <sys_created_by>lhyunseok</sys_created_by>
        <sys_created_on>2024-05-27 05:38:26</sys_created_on>
        <sys_id>3bbb2da393dac2104d95f55a7bba10b3</sys_id>
        <sys_mod_count>0</sys_mod_count>
        <sys_name>x_yergb_bpm_bpm_search_profile_default_spell_check_dictionary</sys_name>
        <sys_package display_value="BPM" source="x_yergb_bpm">41c8a9e73b1e4a10ec3cbf2a85e45ab7</sys_package>
        <sys_policy/>
        <sys_scope display_value="BPM">41c8a9e73b1e4a10ec3cbf2a85e45ab7</sys_scope>
        <sys_update_name>ais_dictionary_3bbb2da393dac2104d95f55a7bba10b3</sys_update_name>
        <sys_updated_by>lhyunseok</sys_updated_by>
        <sys_updated_on>2024-05-27 05:38:26</sys_updated_on>
        <type>SPELLCHECK</type>
    </ais_dictionary>
</record_update>
